django_pistoke-0.9.11.dist-info/licenses/Oikeudet.txt
pistoke/__init__.py
pistoke/asetukset.py
pistoke/kasittelija.py
pistoke/nakyma.py
pistoke/ohjain.py
pistoke/poistuvat.py
pistoke/protokolla.py
pistoke/pyynto.py
pistoke/testaus.py
pistoke/tyokalut.py
pistoke/management/__init__.py
pistoke/management/commands/__init__.py
pistoke/management/commands/runserver.py
django_pistoke-0.9.11.dist-info/METADATA
django_pistoke-0.9.11.dist-info/WHEEL
django_pistoke-0.9.11.dist-info/entry_points.txt
django_pistoke-0.9.11.dist-info/historia.json
django_pistoke-0.9.11.dist-info/top_level.txt
django_pistoke-0.9.11.dist-info/RECORD
