Metadata-Version: 2.4
Name: django-pistoke
Version: 0.9.11
Summary: Django-Websocket-laajennos
Author-email: Antti Hautaniemi <antti.hautaniemi@me.com>
License-Expression: MIT
Project-URL: Repository, https://github.com/an7oine/django-pistoke.git
Requires-Python: >=3.9
License-File: Oikeudet.txt
Requires-Dist: asgiref>=3.6.0
Requires-Dist: django>=3.2
Requires-Dist: python-mmaare
Provides-Extra: runserver
Requires-Dist: uvicorn[standard]; extra == "runserver"
Provides-Extra: websocket
Requires-Dist: websockets>=8.0; extra == "websocket"
Dynamic: license-file
